bidask/__init__.py
bidask/edge.py
bidask/edge_expanding.py
bidask/edge_rolling.py
bidask-2.1.0.dist-info/LICENSE
bidask-2.1.0.dist-info/METADATA
bidask-2.1.0.dist-info/WHEEL
bidask-2.1.0.dist-info/RECORD
