Metadata-Version: 2.1
Name: bidask
Version: 2.1.0
Summary: Efficient Estimation of Bid-Ask Spreads from Open, High, Low, and Close Prices
Home-page: https://github.com/eguidotti/bidask
License: MIT
Author: Emanuele Guidotti
Author-email: emanuele.guidotti@usi.ch
Requires-Python: >=3.6,<4.0
Classifier: License :: OSI Approved :: MIT License
Classifier: Programming Language :: Python :: 3
Classifier: Programming Language :: Python :: 3.6
Classifier: Programming Language :: Python :: 3.7
Classifier: Programming Language :: Python :: 3.8
Classifier: Programming Language :: Python :: 3.9
Classifier: Programming Language :: Python :: 3.10
Classifier: Programming Language :: Python :: 3.11
Requires-Dist: numpy
Requires-Dist: pandas
Project-URL: Repository, https://github.com/eguidotti/bidask
